{
    "memo": "6c89531ad009fa31d005096bb43b0748d946feeccdf1aaed20c9c7b0e117ce42",
    "projects": [
        {
            "name": "github.com/awalterschulze/gographviz",
            "version": "v2.0",
            "revision": "c84395e536e1a1199093a4e6253d1bee99e4cd2a",
            "packages": [
                ".",
                "ast",
                "internal/errors",
                "internal/lexer",
                "internal/parser",
                "internal/token"
            ]
        },
        {
            "name": "github.com/imdario/go-ulid",
            "branch": "master",
            "revision": "80e2735d1c2c2b1d963bccaa2306f67e5f8d5da9",
            "packages": [
                "."
            ]
        },
        {
            "name": "github.com/pkg/errors",
            "version": "v0.8.0",
            "revision": "3866ebc348c54054262feae422da428fe6cf147d",
            "packages": [
                "."
            ]
        },
        {
            "name": "github.com/scgolang/midi",
            "version": "v0.2.0",
            "revision": "dfadd4211cf395fe7f15c3e2f5107b95df17f3f3",
            "packages": [
                "."
            ]
        },
        {
            "name": "github.com/scgolang/osc",
            "version": "v0.10.0",
            "revision": "c682aec2f858d4243bc62eb441ce897f28f9ef53",
            "packages": [
                "."
            ]
        },
        {
            "name": "github.com/scgolang/sc",
            "branch": "master",
            "revision": "4d9e02c94ab4acee5e24d80355e1dc15a4d13270",
            "packages": [
                "."
            ]
        }
    ]
}
